LICENSE
MANIFEST.in
README.md
setup.cfg
setup.py
django_core/__init__.py
django_core/decorators.py
django_core/exceptions.py
django_core/managers.py
django_core/models.py
django_core.egg-info/PKG-INFO
django_core.egg-info/SOURCES.txt
django_core.egg-info/dependency_links.txt
django_core.egg-info/not-zip-safe
django_core.egg-info/top_level.txt
django_core/auth/__init__.py
django_core/auth/views.py
django_core/contrib/__init__.py
django_core/contrib/admin/__init__.py
django_core/contrib/admin/options.py
django_core/contrib/auth/__init__.py
django_core/contrib/auth/backends.py
django_core/db/__init__.py
django_core/db/models/__init__.py
django_core/db/models/fields.py
django_core/db/models/managers.py
django_core/db/models/mixins/__init__.py
django_core/db/models/mixins/base.py
django_core/db/models/mixins/crud.py
django_core/db/models/mixins/generic.py
django_core/db/models/mixins/tokens.py
django_core/db/models/mixins/urls.py
django_core/forms/__init__.py
django_core/forms/fields.py
django_core/forms/widgets.py
django_core/forms/mixins/__init__.py
django_core/forms/mixins/audit.py
django_core/forms/mixins/common.py
django_core/forms/mixins/paging.py
django_core/forms/mixins/query.py
django_core/forms/mixins/users.py
django_core/html/__init__.py
django_core/html/builders.py
django_core/mail/__init__.py
django_core/mail/sending.py
django_core/mail/templates/django_core/mail/base_email.html
django_core/middleware/__init__.py
django_core/middleware/browser.py
django_core/middleware/geo.py
django_core/migrations/0001_initial.py
django_core/migrations/0002_auto_20150504_1510.py
django_core/migrations/0003_auto_20150504_2227.py
django_core/migrations/__init__.py
django_core/templatetags/__init__.py
django_core/templatetags/collection_tags.py
django_core/templatetags/math_tags.py
django_core/templatetags/url_tags.py
django_core/utils/__init__.py
django_core/utils/api.py
django_core/utils/bad_words.py
django_core/utils/collection_utils.py
django_core/utils/connections.py
django_core/utils/date_parsers.py
django_core/utils/file_utils.py
django_core/utils/list_utils.py
django_core/utils/loading.py
django_core/utils/numbers.py
